chatgpt_mcp/__init__.py
chatgpt_mcp/button_helper.py
chatgpt_mcp/chatgpt_automation.py
chatgpt_mcp/chatgpt_mcp.py
chatgpt_mcp/mcp_tools.py
chatgpt_mcp_plus-1.0.0.dist-info/METADATA
chatgpt_mcp_plus-1.0.0.dist-info/WHEEL
chatgpt_mcp_plus-1.0.0.dist-info/entry_points.txt
chatgpt_mcp_plus-1.0.0.dist-info/licenses/LICENSE
chatgpt_mcp_plus-1.0.0.dist-info/RECORD
